{
  "morning": {
    "title": "Mercado global volátil, mas resiliência econômica em foco",
    "date": "15/04/2026 • 08:30h",
    "body": "<p><strong>Análise de Abertura - Panorama Global e Local</strong></p><p>O cenário internacional apresenta sinais mistos nesta quarta-feira. O índice Nasdaq estende sua sequência de ganhos para 10 sessões, impulsionado por expectativas de desescalada nas tensões com o Irã. Empresas de tecnologia, como Nvidia e Google, são apontadas por analistas em áreas consideradas de interesse para compradores. No setor bancário, o Bank of America reportou aumento nos lucros, seguindo o movimento de seus pares, e classificou a economia dos EUA como 'resiliente'. Contudo, a JPMorgan emitiu um alerta para investidores sobre possíveis fraquezas no mercado.</p><p><strong>Riscos e Oportunidades no Curto Prazo</strong></p><p>A volatilidade global é destacada como um risco iminente, mas também como uma potencial fonte de oportunidades para gestores atentos. No cenário doméstico, discussões sobre a avaliação do mercado brasileiro apontam para perspectivas divergentes, com argumentos tanto para que esteja barato quanto caro. Há uma percepção de que riscos anteriores foram incorporados aos preços, mas com o alerta de que a continuidade do cenário positivo não é uma garantia.</p><p><strong>Tendências em Pagamentos e Custódia</strong></p><p>Dois movimentos estruturais chamam a atenção: a disputa entre stablecoins e bancos tradicionais pelo pagamento de juros aos detentores, e o lançamento de uma carteira de auto-custódia por um dos maiores detentores globais de ouro, refletindo uma busca por maior controle sobre ativos.</p><p><strong>Mercados Futuros e Planejamento</strong></p><p>Os preços dos contratos futuros de Dólar e do Ibovespa para esta quarta-feira são divulgados, oferecendo um termômetro para as expectativas de abertura. Paralelamente, há orientações sobre gestão tributária, sugerindo que investidores considerem ações antecipadas, e não apenas no período do imposto de renda.</p><p><strong>Fontes:</strong> Yahoo Finance (Major gold holder launches self-custody wallet; JPMorgan has stark message for investors on market weakness; Don't wait until next April to lower your tax bill. 6 tax moves to make now.; Dow Jones Futures: Nasdaq Rides 10-Day Win Streak On Iran Hopes; Nvidia, Google In Buy Areas; Bank of America joins big bank peers in reporting rising profits, calls US economy 'resilient'), Trilha dos Juros (Volatilidade global pode ser risco no curto prazo, mas oportunidade para quem sabe; Stablecoins vs. bancos: a disputa pelo pagamento de juros; Dólar Futuro e Ibovespa Futuro: Os melhores preços desta quarta-feira; O Brasil está barato ou está caro? As duas respostas estão corretas; O apocalipse virou desconto, mas o risco é acreditar que a festa é garantida).</p>"
  },
  "coffee": {
    "title": "Mercados sob tensão geopolítica e volatilidade",
    "date": "15/04/2026 • 12:00h",
    "body": "<p><strong>Os mercados financeiros operam com atenção dividida entre dados econômicos robustos nos EUA e tensões geopolíticas que pressionam ativos de risco nesta quarta-feira.</strong></p><p>No cenário doméstico, o foco se volta para a volatilidade. Analistas apontam que a instabilidade global pode representar um risco no curto prazo, mas também criar janelas de oportunidade para investidores com perfil adequado. Paralelamente, observa-se a consolidação de novos modelos de consumo, com o lançamento de serviços de entrega ultra-rápida no Brasil.</p><p>Internacionalmente, os dados econômicos dos Estados Unidos, sob a administração do Presidente Donald Trump, continuam a mostrar resiliência diante de turbulências globais, conforme análise de instituições financeiras. No entanto, a JPMorgan emitiu um alerta contundente para investidores sobre a atual fraqueza observada nos mercados.</p><p>O cenário tecnológico e geopolítico também gera movimentos específicos:</p><ul><li>Ações da ASML caíram aproximadamente 5% após a empresa reportar impacto em seu segmento de negócios na China devido a restrições de exportação.</li><li>No setor de criptoativos, um dos maiores detentores de ouro do mundo lançou uma carteira digital de auto-custódia, movimento visto como um passo em direção à democratização do acesso a ativos seguros.</li><li>Analistas de tecnologia, como Brad Gerstner, mantêm visão positiva sobre empresas como a Snowflake (SNOW), mesmo diante de preocupações setoriais, enquanto plataformas como o Uber (UBER) são avaliadas como possíveis oportunidades após correções recentes.</li></ul><p>A tensão no Oriente Médio permanece um foco crítico, com análises indicando que as sanções econômicas dos EUA contra o Irã, se mantidas, podem levar o país a um cenário de colapso financeiro, potencialmente alterando o cálculo estratégico no conflito regional.</p><p><em>Fontes: Trilha dos Juros (Brasil), Yahoo Finance (Global).</em></p>"
  },
  "evening": {
    "title": "Fechamento: Regulação e Consumo em Foco",
    "date": "15/04/2026 • 18:00h",
    "body": "<p>Os mercados encerraram o dia com atenção voltada para mudanças regulatórias no setor financeiro e sinais de comportamento do consumidor.</p><p><strong>Brasil:</strong> O Banco Central publicou a <strong>Resolução 470</strong>, que altera os requisitos de capital para instituições financeiras, parte de um movimento mais amplo de convergência entre tecnologia e regulação no sistema. No varejo, a expansão das entregas em 15 minutos levanta questões sobre o modelo de negócios e seus custos. Dados econômicos dos <strong>Estados Unidos</strong> continuam a mostrar resiliência, conforme análise que busca afastar conclusões prematuras baseadas em percepções.</p><p><strong>Global:</strong> Em meio a movimentos nos mercados, a <strong>JPMorgan</strong> emitiu uma mensagem aos investidores sobre a recente fraqueza das ações. A <strong>Costco</strong> reportou uma mudança no padrão de gastos de seus clientes. No setor de viagens, a <strong>Booking Holding</strong> demonstra rentabilidade sustentável. Entre os papéis em destaque estão JPMorgan, Oracle, Bloom Energy, Credo Technology e American Airlines. No setor de criptoativos, um grande detentor de ouro lançou uma carteira de auto-custódia.</p><p><strong>Geopolítica:</strong> A administração do presidente <strong>Donald Trump</strong> manteve o bloqueio econômico ao Irã, com análises apontando para potenciais impactos severos na economia iraniana e possíveis implicações no cenário de conflitos regionais.</p><p><strong>Fontes:</strong> Notícias coletadas de portais financeiros nacionais e do Yahoo Finance (Global).</p>"
  },
  "daily_term": {
    "term": "Capital Requerido",
    "definition": "Capital requerido é a quantidade mínima de recursos próprios (dinheiro dos sócios) que uma instituição financeira, como um banco, precisa manter para cobrir possíveis perdas e continuar operando com segurança. É como um 'colchão de segurança' obrigatório, determinado pelos reguladores, que protege os clientes e o sistema financeiro como um todo. Se o capital requerido aumenta, como pode ocorrer com novas regras (ex: Resolução 470 no Brasil), os bancos precisam guardar mais dinheiro, o que pode afetar sua capacidade de emprestar e seus lucros."
  },
  "last_update": "2026-04-15T21:41:31.614298"
}