{
    "by": "default",
    "valid_key": false,
    "results": {
        "currencies": {
            "source": "BRL",
            "USD": {
                "name": "Dollar",
                "buy": 4.9727,
                "sell": 4.9882,
                "variation": -0.068
            },
            "EUR": {
                "name": "Euro",
                "buy": 5.819,
                "sell": 5.8411,
                "variation": -0.409
            },
            "GBP": {
                "name": "Pound Sterling",
                "buy": 6.7139,
                "sell": null,
                "variation": -0.094
            },
            "ARS": {
                "name": "Argentine Peso",
                "buy": 0.0036,
                "sell": null,
                "variation": 0.0
            },
            "CAD": {
                "name": "Canadian Dollar",
                "buy": 3.636,
                "sell": null,
                "variation": -0.146
            },
            "AUD": {
                "name": "Australian Dollar",
                "buy": 3.5591,
                "sell": null,
                "variation": 0.02
            },
            "JPY": {
                "name": "Japanese Yen",
                "buy": 0.0312,
                "sell": null,
                "variation": 0.0
            },
            "CNY": {
                "name": "Renminbi",
                "buy": 0.7276,
                "sell": null,
                "variation": -0.26
            },
            "BTC": {
                "name": "Bitcoin",
                "buy": 416831.946,
                "sell": 416831.946,
                "variation": 4.541
            }
        },
        "stocks": {
            "IBOVESPA": {
                "name": "BM&F BOVESPA",
                "location": "Sao Paulo, Brazil",
                "points": 192845.9,
                "variation": -1.68
            },
            "IFIX": {
                "name": "Índice de Fundos de Investimentos Imobiliários B3",
                "location": "Sao Paulo, Brazil",
                "points": 3937.84,
                "variation": -0.1
            },
            "NASDAQ": {
                "name": "NASDAQ Stock Market",
                "location": "New York City, United States",
                "points": 24604.81,
                "variation": 1.45
            },
            "DOWJONES": {
                "name": "Dow Jones Industrial Average",
                "location": "New York City, United States",
                "points": 49398.54,
                "variation": 0.55
            },
            "CAC": {
                "name": "CAC 40",
                "location": "Paris, French",
                "points": 8156.43,
                "variation": -0.96
            },
            "NIKKEI": {
                "name": "Nikkei 225",
                "location": "Tokyo, Japan",
                "points": 59585.86,
                "variation": 0.4
            }
        },
        "available_sources": [
            "BRL"
        ],
        "taxes": []
    },
    "execution_time": 0.0,
    "from_cache": true
}