{
  "events": [
    {
      "time": "00:30",
      "country": "JP",
      "event": "Produção Industrial (MoM) (Fev)",
      "impact": "High",
      "atual": "-2.0%",
      "proj": "-2.1%",
      "prev": "4.3%",
      "date": "14/04"
    },
    {
      "time": "00:30",
      "country": "JP",
      "event": "Utilização da Capacidade (MoM) (Fev)",
      "impact": "High",
      "atual": "-0.1%",
      "proj": "---",
      "prev": "2.9%",
      "date": "14/04"
    },
    {
      "time": "02:00",
      "country": "DE",
      "event": "WPI Alemão (YoY) (Mar)",
      "impact": "High",
      "atual": "4.1%",
      "proj": "---",
      "prev": "1.2%",
      "date": "14/04"
    },
    {
      "time": "02:00",
      "country": "DE",
      "event": "WPI Alemão (MoM) (Mar)",
      "impact": "High",
      "atual": "2.7%",
      "proj": "0.4%",
      "prev": "0.6%",
      "date": "14/04"
    }
  ],
  "last_update": "14/04/2026 20:09:00"
}